dc43_core/__init__.py
dc43_core/odcs.py
dc43_core/odps.py
dc43_core/versioning.py
dc43_core-0.32.0.0.dist-info/METADATA
dc43_core-0.32.0.0.dist-info/WHEEL
dc43_core-0.32.0.0.dist-info/top_level.txt
dc43_core-0.32.0.0.dist-info/RECORD
