Metadata-Version: 2.4
Name: dc43-core
Version: 0.32.0.0
Summary: Shared contract helpers for dc43 packages
Author: Andy Petrella
Classifier: Programming Language :: Python :: 3
Classifier: License :: OSI Approved :: MIT License
Classifier: Operating System :: OS Independent
Requires-Python: >=3.11
Requires-Dist: open-data-contract-standard==3.0.2
